Workbook

Sheet DATA INPUT 
B2: Name of shop | C2: M/S.SHAS DESIGN AND PRINTING
B3: NAME OF BUILDING & LAND MARK /PLACE | C3: NEAR POST OFFICE, NILESHWAR
B4: BUILDING NO. | C4: W-III/1022
B5: GST NO.
B6: MONTHLY RENT OF SHOP | C6: 5500
B7: VILLAGE | C7: NILESHWAR
B8: MUNICIPALITY | C8: NILESHWAR
B9: POST OFFICE | C9: NILESHWAR
B10: TALUK | C10: HOSDURG
B11: BLOCK | C11: NILESHWAR
B12: DISTRICT | C12: KASARAGOD
B13: PIN CODE | C13: 671314
B14: AS PER ADHAR CARD
B15: GENDER | C15: MALE
B16: NAME OF PROPRIETOR | C16: SHAFEEK N N
B17: W/O S/O D/O | C17: S/o.
B18: Name of Father | C18: M MOIDEEN
B19: HOUSE NAME | C19: BAITHUL SHAMNA HOUSE
B20: VILLAGE | C20: KANHANGAD
B21: MUNICIPALITY | C21: NILESHWAR
B22: POST OFFICE | C22: OZHINJAVALAPPU
B23: TALUK | C23: HOSDURG
B24: BLOCK | C24: NILESHWAR
B25: DISTRICT | C25: KASARAGOD
B26: CONTACT NUMBER | C26: 9847599008
B27: PIN CODE | C27: 671314
B28: Date Of Birth | C28: 10/05/1988
B29: PAN No: | C29: EVOPS0533P
B30: ADHAAR CARD NO. | C30: 3616 3601 1234
B31: Line of activity | C31: SERVICE
B32: Status of the unit | C32: FRESH
B33: Qualification | C33: SSLC
B34: Experience (Yrs) in this field | C34: 12
B35: Proposed Business | C35: DIGITAL PRINTING
B36: Scheme of Loan | C36: MUDRA
B37: No. Of YEARS Loan Required | C37: 5
B38: NAMEOF BANK | C38: FEDERAL BANK
B39: BRANCH | C39: NILESHWAR
B41: IT SHOULBE SHOWN AFTER THE MACHINE & WC
B42: TOTAL PROJECT COST
B43: LOAN AMOUNT REQUIRED
G44: =150000*118% -> 177000
B50: DETAILS OF MACHINARY & FIXED ASSET
C51: PARTICULARS | E51: RATE | F51: QTY | G51: AMOUNT
C53: INTEIOR DECORATION | E53: 100000 | F53: 1 | G53: =F53*E53 -> 100000
B54: 2 | C54: XEROX COLOR PRINTER | E54: 521560 | F54: 1 | G54: =F54*E54 -> 521560
B55: 3 | C55: STICKER SCORING MACHINE | E55: 177000 | F55: 1 | G55: =F55*E55 -> 177000
C56: COMPUTER SYSTEM 13-10TH GEN | E56: 36600 | F56: 3 | G56: =F56*E56 -> 109800
C57: INVERTOR 3KVA | E57: 75000 | F57: 1 | G57: =F57*E57 -> 75000
C58: GODREREJ A/C | E58: 35000 | F58: 1 | G58: =F58*E58 -> 35000
C59: LLOYD A/C | E59: 35000 | F59: 1 | G59: =F59*E59 -> 35000
C60: HALER A/C | E60: 40000 | F60: 1 | G60: =F60*E60 -> 40000
C61: COMPUTER CHAIR , TABLE Etc. | E61: 75000 | F61: 1 | G61: =F61*E61 -> 75000
I65: 119396
G78: =SUM(G52:G71) -> 1168360
B80: WORKING CAPITAL
C83: PARTICULARS | E83: RATE | F83: QTY | G83: AMOUNT
C86: TONER | E86: 12000 | F86: 4 | G86: =F86*E86 -> 48000 | H86: =G86*118/100 -> 56640 | I86: 18
C87: CLEAR STICKER BUNDLE | E87: 15 | F87: 1000 | G87: =F87*E87 -> 15000 | H87: =G87*118/100 -> 17700 | I87: 18
C88: PAPER STICKER BUNDLE | E88: 7 | F88: 1000 | G88: =F88*E88 -> 7000 | H88: =G88*118/100 -> 8260 | I88: 18
C89: VINYL STICKER | E89: 15 | F89: 500 | G89: =F89*E89 -> 7500 | H89: =G89*118/100 -> 8850 | I89: 18
C90: 100 GSM PAPER BUNDLE | E90: 2 | F90: 3000 | G90: =F90*E90 -> 6000 | H90: =G90*118/100 -> 7080 | I90: 18
C91: 170 GSM PA[PER BUNDLE | E91: 3 | F91: 2500 | G91: =F91*E91 -> 7500 | H91: =G91*118/100 -> 8850 | I91: 18
C92: 220 GSM PAPER BUNDLE | E92: 4 | F92: 4000 | G92: =F92*E92 -> 16000 | H92: =G92*118/100 -> 18880 | I92: 18
C93: 300GSM PAPER BUNDLE | E93: 5 | F93: 2000 | G93: =F93*E93 -> 10000 | H93: =G93*118/100 -> 11800 | I93: 18
H94: =G94*118/100 -> 0 | I94: 18
H95: =G95*118/100 -> 0 | I95: 18
H96: =G96*118/100 -> 0 | I96: 18
H97: =G97*118/100 -> 0 | I97: 18
H98: =G98*118/100 -> 0 | I98: 18
H99: =G99*118/100 -> 0 | I99: 18
H100: =G100*118/100 -> 0 | I100: 18
H101: =G101*118/100 -> 0 | I101: 18
H102: =G102*118/100 -> 0 | I102: 18
H103: =G103*118/100 -> 0 | I103: 18
H104: =G104*118/100 -> 0 | I104: 18
H105: =G105*118/100 -> 0 | I105: 18
... H108: =G108*118/100 -> 0 | I108: 18
H109: =SUM(H86:H108) -> 138060
I111: =H109+I65 -> 257456
G160: =SUM(G84:G159) -> 117000
C161: GST % 18 | G161: =G160*18/100 -> 21060
G162: =SUM(G160:G161) -> 138060
B163: SALES
C164: PARTICULARS | E164: RATE | F164: QTY /KG | G164: AMOUNT
B166: INPUT AREA MATTERS | C166: PRINTING CHARGES (STICKERS ) | E166: 15 | F166: 15000 | G166: 225000
C167: PRINTING CHARGES (VINYL ) | E167: 25 | F167: 2500 | G167: 62500
C168: DESIGNING CAHRGES | E168: 250 | F168: 300 | G168: 75000
C169: MOMENTOS WITH PRITING | E169: 500 | F169: 50 | G169: 25000
G171: 387500
C173: GST COLLECTED @ | D173: 18% | G173: 69750
E175: total | G175: 457250
F205: -

Sheet INTRODUCTION 
B3: PROJECT –REPORT
E4: ON
B5: ='PROJECT REPORT '!H6 -> M/S.SHAS DESIGN AND PRINTING | H5: ='DATA INPUT '!C3 -> NEAR POST OFFICE, NILESHWAR
D6: PROMOTED BY : | H6: ='DATA INPUT '!C8 -> NILESHWAR
D7: ='PROJECT REPORT '!H17 -> Mr.SHAFEEK N N | G7: Cell No: | I7: ='DATA INPUT '!C26 -> 9847599008
D8: ='DATA INPUT '!C19 -> BAITHUL SHAMNA HOUSE
D9: ='DATA INPUT '!C21 -> NILESHWAR
D10: ='DATA INPUT '!C12 -> KASARAGOD
B41: FINANCE applied to
B43: ='DATA INPUT '!C38 -> FEDERAL BANK
B46: ='DATA INPUT '!$C$39 -> NILESHWAR
B59: v 1) INTRODUCTION
B62: v 2) PROJECT PARTICULARS
B65: v 3) SOURCE OF FINANCE
B68: v 4) COST OFMAINTAINENCE PER MONTH
B71: v 5) ANNUAL SALES TURNOVER AND REALISATION
B74: v 6) BREAK EVEN ANALYSIS
B77: v 7) DEBT SERVICE COVERAGE RATIO
B80: v 8) CASH FLOW
B83: v 9) PROJECTIONS OF PERFORMANCE & PROFITABILTY
B86: v 10) CONCLUSION
B97: 1.INTRODUCTION
B99: A well experienced Individual with sufficient background in his endeavor has proposed to set up a
B100: ='DATA INPUT '!C35 -> DIGITAL PRINTING
B101: unit under the name and style of
B102: =B5 -> M/S.SHAS DESIGN AND PRINTING
C103: ='DATA INPUT '!C3 -> NEAR POST OFFICE, NILESHWAR
C104: ='DATA INPUT '!C7 -> NILESHWAR
C105: =D10 -> KASARAGOD
C106: KERALA PIN - | E106: ='DATA INPUT '!C13 -> 671314
B109: Now-a-days, every activities of social and personal gathering increases the demand on printing
B110: Medias, such as flex banners, signage, advertisement posters, invitations cards etc… Such demands
B111: are met by a highly mechanized and computerized printing enterprise. A graphic printing enterprise
B112: provides each and every required printing medias to its users with a products and services ranging
B113: from low-end printing medias for single use to high quality printing medias
B119: PROMOTER
B121: The Proprietor and the sole owner of the unit is
B122: =D7 -> Mr.SHAFEEK N N
B123: ='DATA INPUT '!C17 -> S/o. | D123: ='PROJECT REPORT '!H18 -> M MOIDEEN
B124: Residing at | D124: ='DATA INPUT '!C19 -> BAITHUL SHAMNA HOUSE
B125: Pachayath | D125: ='DATA INPUT '!C21 -> NILESHWAR
B126: District | D126: ='DATA INPUT '!C25 -> KASARAGOD | F126: ='DATA INPUT '!C27 -> 671314
B127: ='PROJECT REPORT '!R12 -> He | C127: is well expert,having thourogh knowledge by working in so many flux & desiging firms , though
B128: ='DATA INPUT '!C34 -> 12 | C128: Years of working experience in the same field.The promoter believes in sustained
B129: quality service and value to every customer.The rate planned for customers is almost comparitively
B130: lower in market to attract the customers and service is very high in rating The promoter has the skill
B131: to develop the business with innovative skill and ideas by watching the present market condition
B132: and forecast what trends will come in future also and make business strategy on this basis.
B133: The Promoter had prior experience in beauty parlour service and items trading , then deceided to
B134: start the business as an own business.
O143: s
B145: LOCATION
B147: The unit is proposed to be set up at the
E148: RENTED BUILDING
D149: No: | E149: ='DATA INPUT '!C4 -> W-III/1022
E150: ='DATA INPUT '!C3 -> NEAR POST OFFICE, NILESHWAR
E151: ='DATA INPUT '!C8 -> NILESHWAR
E152: ='PROJECT REPORT '!H13 -> HOSDURG | F152: Taluk
E153: ='PROJECT REPORT '!H14 -> KASARAGOD | F153: District | G153: ='DATA INPUT '!C13 -> 671314
B154: The location is well suited for the proposed activity and all infrastructure facilities like availabilty
B155: of employees,transportation and amble parking etc for the unit .
B158: MARKET POTENTIAL
B160: Stickers and printing market in India is growing rapidly nowadays. Additionally, the item is the most
B161: popular tool for any type of outdoor and as well indoor advertising. We can see a growing demand
B162: in almost every city in all over Kerala .
B163: Some of the most potential consumers are regional and national political parties.
B164: Some of the most potential consumers are regional and national political parties. They use banners
B165: in almost every programs and rally. Additionally, companies operating in the several industries use
B166: banners for various purposes. Apart from the digital signage, flex is the only instrument for outdoor
B167: media advertising. Furthermore, every school, educational institutions, and sports organizations
B168: use flex ,banners in almost every event. Additionally, there is good domestic market also.
... B219: can achieve the the desired target of turnover and profit also.

Sheet PROJECT REPORT 
D3: 1.PROJECT HIGHLIGHTS
N4: YEAR OF LOAN
N5: 5
B6: Name Of Unit , Loaction & Address | H6: ='DATA INPUT '!C2 -> M/S.SHAS DESIGN AND PRINTING | N6: PENDING MONTHS IN THIS FINANCIAL YEAR
H7: ='DATA INPUT '!C3 -> NEAR POST OFFICE, NILESHWAR | N7: 8
B8: Building No. | H8: ='DATA INPUT '!C4 -> W-III/1022 | N8: 15 | O8: =MONTH(B847) -> 8 | P8: UPTO DEC WORK OUT
O9: =N8-O8 -> 7 | R9: =IF(O12="MALE",("his"),("her")) -> his
B10: Village | H10: ='DATA INPUT '!C8 -> NILESHWAR | N10: count from present month to next march
B11: Muicipalty/Panchayath | H11: ='DATA INPUT '!C8 -> NILESHWAR | O11: ='DATA INPUT '!C16 -> SHAFEEK N N
B12: Block | H12: ='DATA INPUT '!C11 -> NILESHWAR | O12: ='DATA INPUT '!C15 -> MALE | R12: =IF(O12="MALE",("He"),("She")) -> He
B13: Taluk | H13: ='DATA INPUT '!C10 -> HOSDURG
B14: District | H14: ='DATA INPUT '!C12 -> KASARAGOD | R14: IF FUNCTION KEY
B15: PIN | H15: ='DATA INPUT '!C13 -> 671314 | R15: 2
B16: Cell No: | H16: ='DATA INPUT '!C26 -> 9847599008 | N16: WORKING CAPITAL | P16: =IF(O21="PMEGP",(1),(3)) -> 3
B17: Chief Executive Name | H17: =IF(O12="MALE",("Mr."&O11),"Mrs."&O11) -> Mr.SHAFEEK N N | N17: Rqrd for Monyhly | O17: divided by 1 | S17: 3 MONTHS SALES REVENUE
B18: ='DATA INPUT '!B18 -> Name of Father | H18: ='DATA INPUT '!C18 -> M MOIDEEN | N18: Rqrd for Quarterly | O18: divided by 3
B19: Address | H19: ='DATA INPUT '!C19 -> BAITHUL SHAMNA HOUSE
H20: ='DATA INPUT '!C20 -> KANHANGAD | N20: MUDRA LOAN | O20: 0.75 | S20: IF (K11 >M13,"3MONTHS SALES REVENUE)
H21: ='DATA INPUT '!C11 -> NILESHWAR | O21: ='DATA INPUT '!C36 -> MUDRA | P21: 75 | S21: IF (K11 <M13,"MONTHLY SALES REVENUE)
H22: ='DATA INPUT '!C25 -> KASARAGOD | N22: PMEGP LOAN | O22: 0.95
H23: ='DATA INPUT '!C27 -> 671314
B24: Age, Date Of Birth | H24: ='DATA INPUT '!C28 -> 10/05/1988 | N24: NO. OF WORKERS | O24: NO. OF MACHINE WHICH IS HIGH ) | P24: =(J361/100000)+0.7 -> 8.51
B25: PAN No: | N25: Term loan amt divided by 1 lakh | P25: =ROUND(P24,0) -> 9
B26: ADHAAR CARD NO. | H26: ='DATA INPUT '!C30 -> 3616 3601 1234 | N26: without decimal , to nxt full digit
B27: Line of activity | H27: ='DATA INPUT '!C31 -> SERVICE
B28: Proposed Business | H28: ='DATA INPUT '!C35 -> DIGITAL PRINTING | N28: PERCENTAGE OF BANK LOAN INT. | P28: 10.5
B29: Status of the unit | H29: ='DATA INPUT '!C32 -> FRESH
B30: Qualification | H30: ='DATA INPUT '!C33 -> SSLC
B31: Yearsof Experience in this field | H31: ='DATA INPUT '!C34 -> 12 | N31: AUDIT FEE | R31: WC | S31: IF (M30 >M31,"1000)
N32: W.C UPTO 5 LAKH | O32: 500 | R32: =J307 -> 139830 | S32: IF (M30<M31,"500)
B33: Scheme of Loan | H33: OFOE | P33: =IF(R32>R33,"1000","500") -> 500 | R33: 500000
B34: Details of collateral security | H34: MACHINARY & STOCK | N34: W.C ABOVE 5 LAKH | O34: 1000
B35: Fixed Capital | H35: =L167 -> 781000 | O35: NOT LINKED
B36: working Capital | H36: =F308 -> 139830 | N36: DATE: FOR SUSHIL ONLY cuurent datein PR & + 5 days IN BANK APLLICATION
B37: Total Cost Of the Project | H37: =J365 -> 920830
B38: Means of Finance | N38: No. Of months loan required | P38: ='DATA INPUT '!C37*12 -> 60
B39: a) Own fund | H39: =F365 -> 285080
B40: b)Term Loan | H40: =H361 -> 585750 | N40: CHITTY | P40: =H41*5/100/2*12 -> 15000
B41: c)Working Capital loan | H41: =H363 -> 50000
B42: Total | H42: =SUM(H39:H41) -> 920830
N43: PERCENTAGE OF EXPENSES | P43: 0.85to 6
B44: Total Connected load | H44: 1hp | N44: ON WORKING CAPITAL
B45: Employemnt Potential | H45: =F393 -> 3
B46: Expected Sales Per annum | H46: =L471*12 -> 1829000 | N46: Transportation | O46: =J307*P46/100 -> 908.895 | P46: 0.65
B47: Operating Profit | H47: =J492 -> 388708.03 | N47: Electricity charges | O47: =J307*P47/100 -> 419.49 | P47: 0.3
B48: Break Even Point -BEP | H48: =L596 -> 40.709619 | N48: Printing & Stationary | O48: =J307*P48/100 -> 125.847 | P48: 0.09
B49: Debt Service Coverage Ratio | H49: =D632 -> 2.8407488 | J49: :1 | N49: Telephone & internrt charges | O49: =J307*P49/100 -> 125.847 | P49: 0.09
B50: Land & Building | J50: RENTED Per YEAR in Rs. | N50: Repairs & others | O50: =J307*P50/100 -> 489.405 | P50: 0.35
J51: ='DATA INPUT '!C6*12 -> 66000 | N51: Advertisement Charges | O51: =J307*P51/100 -> 559.32 | P51: 0.4
B52: FINANCING BANK | H52: ='DATA INPUT '!C38 -> FEDERAL BANK | N52: Miscellaneous expenses | O52: =J307*P52/100 -> 978.81 | P52: 0.7
H53: ='DATA INPUT '!C39 -> NILESHWAR
N58: GST rate : | O58: 5-18% | P58: 18
N61: DEPRECIATION
N62: MONTHS EQUATION | O62: =N7 -> 8 | P62: Dep.AMT
N63: =J361 -> 781000 | O63: =N63*10/100/12*N7 -> 52066.667 | P63: =O63*100/N63 -> 6.6666667
N64: =N63-O63 -> 728933.33 | O64: =N64*10/100 -> 72893.333 | P64: =O64*100/N63 -> 9.3333333
N65: =N64-O64 -> 656040 | O65: =N65*10/100 -> 65604 | P65: =O65*100/N63 -> 8.4
N66: =N65-O65 -> 590436 | O66: =N66*10/100 -> 59043.6 | P66: =O66*100/N63 -> 7.56
N67: =N66-O66 -> 531392.4 | O67: =N67*10/100 -> 53139.24 | P67: =O67*100/N63 -> 6.804
N68: =N67-O67 -> 478253.16 | O68: =N68*10/100 -> 47825.316 | P68: =O68*100/N64 -> 6.561
D69: 2. PROJECT PARTICULARS | N69: =N68-O68 -> 430427.84 | O69: =N69*10/100 -> 43042.784 | P69: =O69*100/N65 -> 6.561
N71: HAS TO ENTER
N72: AUTOMATIC
B74: A.FIXED INVESTMENTS
B76: (a) Land & Building
B78: (b) Plant & Equipments
B80: MACHINARY ,FURNITURES & FITTINGS
B82: PARTICULARS | D82: RATE | F82: QTY | H82: AMOUNT
B85: ='DATA INPUT '!C54 -> XEROX COLOR PRINTER | D85: 401200 | F85: ='DATA INPUT '!F54 -> 1 | H85: =D85*F85 -> 401200
B87: ='DATA INPUT '!C56 -> COMPUTER SYSTEM 13-10TH GEN | D87: ='DATA INPUT '!E56 -> 36600 | F87: ='DATA INPUT '!F56 -> 3 | H87: =D87*F87 -> 109800
B88: ='DATA INPUT '!C57 -> INVERTOR 3KVA | D88: ='DATA INPUT '!E57 -> 75000 | F88: ='DATA INPUT '!F57 -> 1 | H88: =D88*F88 -> 75000
B89: ='DATA INPUT '!C58 -> GODREREJ A/C | D89: ='DATA INPUT '!E58 -> 35000 | F89: ='DATA INPUT '!F58 -> 1 | H89: =D89*F89 -> 35000
B90: ='DATA INPUT '!C59 -> LLOYD A/C | D90: ='DATA INPUT '!E59 -> 35000 | F90: ='DATA INPUT '!F59 -> 1 | H90: =D90*F90 -> 35000
B91: ='DATA INPUT '!C60 -> HALER A/C | D91: ='DATA INPUT '!E60 -> 40000 | F91: ='DATA INPUT '!F60 -> 1 | H91: =D91*F91 -> 40000
B92: ='DATA INPUT '!C61 -> COMPUTER CHAIR , TABLE Etc. | D92: 85000 | F92: ='DATA INPUT '!F61 -> 1 | H92: =D92*F92 -> 85000
B93: ='DATA INPUT '!C62 -> 0 | D93: ='DATA INPUT '!E62 -> 0 | F93: ='DATA INPUT '!F62 -> 0 | H93: =D93*F93 -> 0
B94: ='DATA INPUT '!C63 -> 0 | D94: ='DATA INPUT '!E63 -> 0 | F94: ='DATA INPUT '!F63 -> 0 | H94: =D94*F94 -> 0
B95: ='DATA INPUT '!C62 -> 0 | D95: ='DATA INPUT '!E62 -> 0 | F95: ='DATA INPUT '!F62 -> 0 | H95: =D95*F95 -> 0
B96: ='DATA INPUT '!C63 -> 0 | D96: ='DATA INPUT '!E63 -> 0 | F96: ='DATA INPUT '!F63 -> 0 | H96: =D96*F96 -> 0
B97: ='DATA INPUT '!C64 -> 0 | D97: ='DATA INPUT '!E64 -> 0 | F97: ='DATA INPUT '!F64 -> 0 | H97: =D97*F97 -> 0
B98: ='DATA INPUT '!C65 -> 0 | D98: ='DATA INPUT '!E65 -> 0 | F98: ='DATA INPUT '!F65 -> 0 | H98: =D98*F98 -> 0
B99: ='DATA INPUT '!C66 -> 0 | D99: ='DATA INPUT '!E66 -> 0 | F99: ='DATA INPUT '!F66 -> 0 | H99: =D99*F99 -> 0
B100: ='DATA INPUT '!C67 -> 0 | D100: ='DATA INPUT '!E67 -> 0 | F100: ='DATA INPUT '!F67 -> 0 | H100: =D100*F100 -> 0
B101: ='DATA INPUT '!C68 -> 0 | D101: ='DATA INPUT '!E68 -> 0 | F101: ='DATA INPUT '!F68 -> 0 | H101: =D101*F101 -> 0
B102: ='DATA INPUT '!C69 -> 0 | D102: ='DATA INPUT '!E69 -> 0 | F102: ='DATA INPUT '!F69 -> 0 | H102: =D102*F102 -> 0
B103: ='DATA INPUT '!C70 -> 0 | D103: ='DATA INPUT '!E70 -> 0 | F103: ='DATA INPUT '!F70 -> 0 | H103: =D103*F103 -> 0
B104: ='DATA INPUT '!C71 -> 0 | D104: ='DATA INPUT '!E71 -> 0 | F104: ='DATA INPUT '!F71 -> 0 | H104: =D104*F104 -> 0
B105: ='DATA INPUT '!C72 -> 0 | D105: ='DATA INPUT '!E72 -> 0 | F105: ='DATA INPUT '!F72 -> 0 | H105: =D105*F105 -> 0
B106: ='DATA INPUT '!C73 -> 0 | D106: ='DATA INPUT '!E73 -> 0 | F106: ='DATA INPUT '!F73 -> 0 | H106: =D106*F106 -> 0
... B108: ='DATA INPUT '!C75 -> 0 | D108: ='DATA INPUT '!E75 -> 0 | F108: ='DATA INPUT '!F75 -> 0 | H108: =D108*F108 -> 0
B165: TOTAL INCLUDING GST | H165: =SUM(H84:H92) -> 781000
D167: Total | F167: Rs. | H167: =SUM(H165:H165) -> 781000 | L167: =L76+H167 -> 781000
B231: B. WORKING CAPITAL REQUIRMENTS (RAW MATERIALS)
B233: PARTICULARS | F233: RATE | H233: QTY | J233: AMOUNT
B236: ='DATA INPUT '!C86 -> TONER | F236: 3000 | H236: ='DATA INPUT '!F86 -> 4 | J236: =H236*F236 -> 12000
B237: MOMENTOS | F237: 250 | H237: 150 | J237: =H237*F237 -> 37500
B238: ='DATA INPUT '!C87 -> CLEAR STICKER BUNDLE | F238: ='DATA INPUT '!E87 -> 15 | H238: ='DATA INPUT '!F87 -> 1000 | J238: =H238*F238 -> 15000
B239: ='DATA INPUT '!C88 -> PAPER STICKER BUNDLE | F239: ='DATA INPUT '!E88 -> 7 | H239: ='DATA INPUT '!F88 -> 1000 | J239: =H239*F239 -> 7000
B240: ='DATA INPUT '!C89 -> VINYL STICKER | F240: ='DATA INPUT '!E89 -> 15 | H240: ='DATA INPUT '!F89 -> 500 | J240: =H240*F240 -> 7500
B241: ='DATA INPUT '!C90 -> 100 GSM PAPER BUNDLE | F241: ='DATA INPUT '!E90 -> 2 | H241: ='DATA INPUT '!F90 -> 3000 | J241: =H241*F241 -> 6000
...

Sheet T,P&L,BS
B2: =C72 -> M/S.SHAS DESIGN AND PRINTING
A3: TRADING AND PROFIT AND LOSS ACCOUNT FOR THE YEAR ENDED 31ST MARCH 2019
A5: PARTICULARS | C5: AMOUNT | D5: PARTICULARS | F5: AMOUNT
A7: To Opening stock | C7: 534520 | D7: By Sales | F7: 796061
A8: " Purchase | C8: 470500
D9: By Closing Stock | F9: =C78 -> 0
A10: " Gross profit C/d | C10: =F11-C7-C8-C9 -> -208959
A11: TOTAL | C11: =SUM(C7:C10) -> 796061 | D11: TOTAL | F11: =SUM(F6:F10) -> 796061
D13: " Gross profit B/d | F13: =C10 -> -208959
A14: " Salary& wages | C14: 248500
A15: " Electricity charges | C15: 10850
A16: " Repairs | C16: 3450
A17: " Transportation | C17: 8450
A18: " Telephone charges | C18: 5800 | G18: Profit to be come
A19: " Administrative expense | C19: 17500 | G19: 145550
A20: " Printing & stationery | C20: 2850
A21: " Miscellaneous expense | C21: 12350 | G21: =G19-C24 -> 706259
A22: " Depreciation | C22: =G46 -> 0
A23: " Rent | C23: 42000
A24: " Net Profit | C24: =F26-C14-C15-C16-C17-C18-C19-C20-C21-C22-C23 -> -560709
A26: TOTAL | C26: =SUM(C13:C25) -> -208959 | D26: TOTAL | F26: =SUM(F13:F25) -> -208959
D29: =B2 -> M/S.SHAS DESIGN AND PRINTING
D32: Proprietor
B37: =C72 -> M/S.SHAS DESIGN AND PRINTING
A38: BALANCE SHEET AS AT 31ST MARCH 2019
A39: LIABILITIES | B39: AMOUNT | C39: AMOUNT | D39: ASSETS | E39: AMOUNT | F39: AMOUNT
D40: FIXED ASSETS
A41: CAPITAL ACCOUNT | B41: 533897
A42: Add : Net profit | B42: =C24 -> -560709 | D42: =D115 -> MACHINERY & FITTINGS | E42: =I42 -> 0 | I42: =J42*111.1111/100 -> 0
B43: =SUM(B41:B42) -> -26812 | D43: Less depreciation | E43: =E42*10/100 -> 0 | F43: =E42-E43 -> 0
A44: Less : drawings | B44: 60000 | C44: =B43-B44 -> -86812 | D44: =D117 -> 0 | E44: =I44 -> 0 | I44: =J44*111.1111/100 -> 0
D45: Less depreciation | E45: =E44*10/100 -> 0 | F45: =E44-E45 -> 0 | G45: depreciation
D46: =D120 -> 0 | E46: =I46 -> 0 | G46: =E43+E45+E47 -> 0 | I46: =J46*111.1111/100 -> 0
D47: Less depreciation | E47: =E46*10/100 -> 0 | F47: =E46-E47 -> 0
G48: total asset
G49: =E42+E44+E46 -> 0
A51: SUNDRY CREDITORS | C51: 498305 | D51: CLOSING STOCK | F51: 745350
D53: SUNDRY DEBTORS | F53: 15580
G55: DIFFERENCE
D56: CASH AND BANK BALANCES | G56: =C58-F58 -> -362017
D57: CASH- IN- HAND | F57: 12580
A58: TOTAL | C58: =SUM(C41:C57) -> 411493 | D58: TOTAL | F58: =SUM(F42:F57) -> 773510
D61: =D29 -> M/S.SHAS DESIGN AND PRINTING
D63: Proprietor
B64: CASH IN BANK | D64: 12000
B72: ='PROJECT REPORT '!H17 -> Mr.SHAFEEK N N | C72: ='PROJECT REPORT '!H6 -> M/S.SHAS DESIGN AND PRINTING
B73: ='PROJECT REPORT '!H7 -> NEAR POST OFFICE, NILESHWAR | C73: ='DATA INPUT '!C11 -> NILESHWAR
A74: ESTIMATED TRADING AND PROFIT AND LOSS ACCOUNT FOR THE YEAR ENDED 31ST MARCH 2026
A76: PARTICULARS | C76: AMOUNT | D76: PARTICULARS | F76: AMOUNT
A78: To Opening stock | C78: 0 | D78: By Sales Revenue ( Less S. Returns) | F78: ='PROJECT REPORT '!D753*100000-G79 -> 1088983.3 | G78: difference
A79: " Purchases (Including GST) | C79: ='PROJECT REPORT '!D757*100000 -> 372880 | G79: =F82-C78 -> 130350
A82: " Gross profit C/d | C82: =F83-C78-C79-C81 -> 846453.33 | D82: " Closing Stock | F82: ='PROJECT REPORT '!J303*110/100 -> 130350
A83: TOTAL | C83: =SUM(C78:C82) -> 1219333.3 | D83: TOTAL | F83: =SUM(F77:F82) -> 1219333.3
A84: " Salary& wages | C84: ='PROJECT REPORT '!D763*100000 -> 256000 | D84: " Gross profit B/d | F84: =C82 -> 846453.33
A85: " Electricity charges | C85: ='PROJECT REPORT '!D779*100000 -> 3200
A86: " Repairs | C86: ='PROJECT REPORT '!D761*100000 -> 4000
A87: " Transportation | C87: ='PROJECT REPORT '!D786*100000 -> 7200
A88: " Telephone charges | C88: ='PROJECT REPORT '!D769*100000 -> 800
A89: " Advertisement Charges | C89: ='PROJECT REPORT '!D765*100000 -> 4800
A90: " Printing & stationery | C90: ='PROJECT REPORT '!D767*100000 -> 800 | G90: Profit to be come
A91: " Bank Interest | C91: ='PROJECT REPORT '!D790*100000 -> 39035.5 | G91: ='PROJECT REPORT '!D796*100000 -> 292139.97
A92: " Miscellaneous expense | C92: ='PROJECT REPORT '!D771*100000 -> 8000
A93: " Depreciation | C93: ='PROJECT REPORT '!D788*100000 -> 52066.667
A94: " Rent | C94: ='PROJECT REPORT '!D759*100000 -> 44000 | G94: =G91-C98 -> 0
A95: " GST Paid | C95: ='PROJECT REPORT '!D773*100000 -> 129120
A96: " Cess Paid | C96: ='PROJECT REPORT '!D775*100000 -> 1291.2
A97: " Audit fee Paid | C97: ='PROJECT REPORT '!D777*100000 -> 4000
A98: " Net Profit | C98: =F100-C84-C85-C86-C87-C88-C89-C90-C91-C92-C93-C94-C95-C96-C97 -> 292139.97
A100: TOTAL | C100: =SUM(C84:C99) -> 846453.33 | D100: TOTAL | F100: =SUM(F84:F99) -> 846453.33
H101: =E115*10/100/12*4 -> 26033.333
C102: For | D102: =D61 -> M/S.SHAS DESIGN AND PRINTING
A103: ='PROJECT REPORT '!B846 -> NILESHWAR
A104: ='PROJECT REPORT '!B847 -> 45896
D105: =D63 -> Proprietor
B109: =B72 -> Mr.SHAFEEK N N | C109: =C72 -> M/S.SHAS DESIGN AND PRINTING
B110: =B73 -> NEAR POST OFFICE, NILESHWAR | C110: =C73 -> NILESHWAR | H110: net sales | J110: =F78 -> 1088983.3
A111: ESTIMATED BALANCE SHEET AS AT 31ST MARCH 2026 | H111: net profit | J111: =C98 -> 292139.97 | K111: net profit | L111: x 100
A112: LIABILITIES | B112: AMOUNT | C112: AMOUNT | D112: ASSETS | E112: AMOUNT | F112: AMOUNT | H112: net profit margin ratio | J112: =J111/J110*100 -> 26.826854 | K112: netsales
A113: NON CURRENT LIABILITIES | D113: FIXED ASSETS | G113: depreciation
A114: CAPITAL ACCOUNT | B114: ='PROJECT REPORT '!F365 -> 285080 | D114: Tangible Asset (Machinary & Tools ) | G114: ='Depreciation Schedule'!E67 -> 18000 | K114: net sales
A115: Add : Net profit | B115: =C98 -> 292139.97 | D115: MACHINERY & FITTINGS | E115: ='PROJECT REPORT '!L167 -> 781000 | H115: Asset turn over ratio | J115: =J110/F135 -> 0.9548493 | K115: average of net assets (PREV.YEAR (begingASSET+ current (ending yearsset/2
B116: =SUM(B114:B115) -> 577219.97 | D116: Less Depreciation | E116: =E115*10/100/12*'PROJECT REPORT '!O62 -> 52066.667 | F116: =E115-E116 -> 728933.33
A117: Less : Drawings | B117: ='PROJECT REPORT '!D662*100000 -> 40000 | H117: cogs | J117: =(C78+C79)-F82 -> 242530 | K117: cost of goods sold (starting stock+purchase - ending stock)
B118: =C118 -> 537219.97 | C118: =B116-B117 -> 537219.97 | H118: invetory turn over ratio | J118: =J117/J119 -> 3.7212121 | K118: Average inventory (beginig + ending stock/2)
A119: LONG TERM CURRENT LIABILITIES | G119: depreciation | H119: average inventory | J119: =C78+F82/2 -> 65175
A120: LOANS AND ADVANCES | G120: =E116+E119+E121 -> 52066.667 | H120: Current Ratio | J120: =J121/J122 -> 9.0237502
A121: TERM LOAN | B121: ='PROJECT REPORT '!F818*100000 -> 507650 | H121: Current asset total | J121: =F124+F125+F126+F127+F128 -> 411543.32 | L121: =H121 -> Current asset total
A122: ='PROJECT REPORT '!H52 -> FEDERAL BANK | D122: CURRENT ASSETS , LOANS AND ADVANCES | G122: total asset | H122: Current liabilty total | J122: =C128+C130+C131+C132+C133 -> 45606.683 | L122: =H122 -> Current liabilty total
A123: CASH CREDIT | B123: ='PROJECT REPORT '!F814*100000 -> 50000 | G123: =E115+E117+E120 -> 781000 | H123: QUICK RATIO | J123: =J124/J122 -> 9.0237502 | L123: CASH+ DRS+ INVENTORY | N123: =J124 -> 411543.32
A124: ='PROJECT REPORT '!H52 -> FEDERAL BANK | B124: =C124 -> 557650 | C124: =B121+B123 -> 557650 | D124: CLOSING STOCK | F124: =F82 -> 130350 | H124: CASH+ DRS+ INVENTORY = | J124: =F126+F125+F124+F127 -> 411543.32 | L124: CURRENT LIABILITY | N124: =J122 -> 45606.683
D125: TRADE RECEIEVABLES(SUNDRY DEBTORS) | F125: =C135-F116-F118-F120-F121-F124-F126-F127-F128 -> 4022.1833
A126: DEFERRED TAX LIABILITIES | C126: 0 | D126: CASH IN HAND | F126: ='PROJECT REPORT '!D666*100000 -> 265171.13 | H126: debt to total asset | J126: =N126/N127 -> 0.039989143 | L126: trade payable+misc payable +mortgage | N126: =C128+C130+C131+C132+C133 -> 45606.683
A127: OTHER CURRENT LIABILITIES | D127: CASH IN BANK | F127: =D64 -> 12000 | L127: total asset | N127: =F135 -> 1140476.6
A128: TRADE PAYABLES( SUNDRY CREDITORS ) | C128: =F78*2.5/100 -> 27224.583 | H128: Debt equity Ratio | J128: =J129/J130 -> 1.4803077 | L128: total short term and long term debt
A129: SHORT TERM PROVISIONS | H129: total short term and long term debt | J129: =C124+C128+C130+C131+C132+C133 -> 603256.68 | L129: stock+ reseve& surplus
A130: ELECTRCITY CHARGES PAYABLE | C130: ='PROJECT REPORT '!L397 -> 400 | H130: stock+ reseve& surplus | J130: =F124+F127+F126 -> 407521.13
A131: TELEPHONE& INTERNET CHARGES PAYABLE | C131: ='PROJECT REPORT '!L401 -> 100
A132: GST & CESS PAYABLE | C132: ='PROJECT REPORT '!L413+'PROJECT REPORT '!L415/'PROJECT REPORT '!N7*12 -> 16382.1 | L132: sales
A133: AUDIT FEE & LEGAL CHARGES PAYABLE | C133: ='PROJECT REPORT '!L417*300/100 -> 1500 | H133: working capital ratio | J133: =J110/J135 -> 2.9758795 | L133: working capital
G134: DIFFERENCE
...

Sheet Depreciation Schedule
B16: ='T,P&L,BS'!B388 -> Mr.SHAFEEK N N | C16: ='T,P&L,BS'!C388 -> M/S.SHAS DESIGN AND PRINTING
A17: ='DATA INPUT '!C3 -> NEAR POST OFFICE, NILESHWAR
B18: DEPRECIATION SCHEDULE OF FIXED ASSET AS ON 31-03-2024
B20: PARTICULARS | C20: % | D20: Rs. Ps. | E20: Rs. Ps. | F20: Rs. Ps.
B22: ='PROJECT REPORT '!B84 -> 0 | D22: ='PROJECT REPORT '!H84 -> 0 | E22: =D22 -> 0
B23: Less: Depreciation Written off | C23: 10 | E23: =E22*10/100/12*'PROJECT REPORT '!O62 -> 0 | F23: =E22-E23 -> 0
B24: ='PROJECT REPORT '!B86 -> 0 | D24: ='PROJECT REPORT '!H86 -> 0 | E24: =SUM(D24:D24) -> 0
B25: Less: Depreciation Written off | C25: 10 | E25: =E24*10/100/12*'PROJECT REPORT '!O62 -> 0 | F25: =E24-E25 -> 0
B26: ='PROJECT REPORT '!B88 -> INVERTOR 3KVA | D26: ='PROJECT REPORT '!H88 -> 75000 | E26: =D26 -> 75000
B27: Less: Depreciation Written off | C27: 10 | E27: =E26*10/100/12*'PROJECT REPORT '!O62 -> 5000 | F27: =E26-E27 -> 70000
B28: ='PROJECT REPORT '!B89 -> GODREREJ A/C | D28: ='PROJECT REPORT '!H89 -> 35000 | E28: =D28 -> 35000
B29: Less: Depreciation Written off | C29: 10 | E29: =E28*10/100/12*'PROJECT REPORT '!O62 -> 2333.3333 | F29: =E28-E29 -> 32666.667
B30: ='PROJECT REPORT '!B90 -> LLOYD A/C | D30: ='PROJECT REPORT '!H90 -> 35000 | E30: =D30 -> 35000
B31: Less: Depreciation Written off | C31: 10 | E31: =E30*10/100/12*'PROJECT REPORT '!O62 -> 2333.3333 | F31: =E30-E31 -> 32666.667
B32: ='PROJECT REPORT '!B91 -> HALER A/C | D32: ='PROJECT REPORT '!H91 -> 40000 | E32: =D32 -> 40000
B33: Less: Depreciation Written off | C33: 10 | E33: =E32*10/100/12*'PROJECT REPORT '!O62 -> 2666.6667 | F33: =E32-E33 -> 37333.333
B34: ='PROJECT REPORT '!B92 -> COMPUTER CHAIR , TABLE Etc. | D34: ='PROJECT REPORT '!H92 -> 85000 | E34: =D34 -> 85000
B35: Less: Depreciation Written off | C35: 10 | E35: =E34*10/100/12*'PROJECT REPORT '!O62 -> 5666.6667 | F35: =E34-E35 -> 79333.333
B36: ='PROJECT REPORT '!B93 -> 0 | D36: ='PROJECT REPORT '!H93 -> 0 | E36: =SUM(D36:D36) -> 0
B37: Less: Depreciation Written off | C37: 10 | E37: =E36*10/100/12*'PROJECT REPORT '!O62 -> 0 | F37: =E36-E37 -> 0
B38: ='PROJECT REPORT '!B94 -> 0 | D38: ='PROJECT REPORT '!H94 -> 0 | E38: =D38 -> 0
B39: Less: Depreciation Written off | C39: 10 | D39: ='PROJECT REPORT '!H102 -> 0 | E39: =E38*10/100/12*'PROJECT REPORT '!O62 -> 0 | F39: =E38-E39 -> 0
B40: ='PROJECT REPORT '!B95 -> 0 | D40: ='PROJECT REPORT '!H95 -> 0 | E40: =D40 -> 0
B41: Less: Depreciation Written off | C41: 10 | E41: =E40*10/100/12*'PROJECT REPORT '!O62 -> 0 | F41: =E40-E41 -> 0
B42: ='PROJECT REPORT '!B96 -> 0 | D42: ='PROJECT REPORT '!H96 -> 0 | E42: =D42 -> 0
B43: Less: Depreciation Written off | C43: 10 | E43: =E42*10/100/12*'PROJECT REPORT '!O62 -> 0 | F43: =E42-E43 -> 0
B44: ='PROJECT REPORT '!B97 -> 0 | D44: ='PROJECT REPORT '!H97 -> 0 | E44: =D44 -> 0
B45: Less: Depreciation Written off | C45: 10 | E45: =E44*10/100/12*'PROJECT REPORT '!O62 -> 0 | F45: =E44-E45 -> 0
B46: ='PROJECT REPORT '!B98 -> 0 | D46: ='PROJECT REPORT '!H98 -> 0 | E46: =D46 -> 0
B47: Less: Depreciation Written off | C47: 10 | E47: =E46*10/100/12*'PROJECT REPORT '!O62 -> 0 | F47: =E46-E47 -> 0
B48: ='PROJECT REPORT '!B99 -> 0 | D48: ='PROJECT REPORT '!H99 -> 0 | E48: =D48 -> 0
B49: Less: Depreciation Written off | C49: 10 | E49: =E48*10/100/12*'PROJECT REPORT '!O62 -> 0 | F49: =E48-E49 -> 0
B50: ='PROJECT REPORT '!B100 -> 0 | D50: ='PROJECT REPORT '!H100 -> 0 | E50: =D50 -> 0
B51: Less: Depreciation Written off | C51: 10 | E51: =E50*10/100/12*'PROJECT REPORT '!O62 -> 0 | F51: =E50-E51 -> 0
B52: ='PROJECT REPORT '!B101 -> 0 | D52: ='PROJECT REPORT '!H101 -> 0 | E52: =D52 -> 0
B53: Less: Depreciation Written off | C53: 10 | E53: =E52*10/100/12*'PROJECT REPORT '!O62 -> 0 | F53: =E52-E53 -> 0
B54: ='PROJECT REPORT '!B102 -> 0 | D54: ='PROJECT REPORT '!H102 -> 0 | E54: =D54 -> 0
B55: Less: Depreciation Written off | C55: 10 | E55: =E54*10/100/12*'PROJECT REPORT '!O62 -> 0 | F55: =E54-E55 -> 0
B56: ='PROJECT REPORT '!B103 -> 0 | D56: ='PROJECT REPORT '!H103 -> 0 | E56: =D56 -> 0
B57: Less: Depreciation Written off | C57: 10 | E57: =E56*10/100/12*'PROJECT REPORT '!O62 -> 0 | F57: =E56-E57 -> 0
B58: ='PROJECT REPORT '!B104 -> 0 | D58: ='PROJECT REPORT '!H104 -> 0 | E58: =D58 -> 0
B59: Less: Depreciation Written off | C59: 10 | E59: =E58*10/100/12*'PROJECT REPORT '!O62 -> 0 | F59: =E58-E59 -> 0
C67: TOTAL | D67: =SUM(D22:D60) -> 270000 | E67: =E23+E25+E27+E29+E31+E33+E35+E37+E39+E41+E43+E45+E47+E49+E51+E53+E55+E5+E57+E59+E61 -> 18000 | F67: =SUM(F22:F61) -> 252000
B205: =B16 -> Mr.SHAFEEK N N | C205: =C16 -> M/S.SHAS DESIGN AND PRINTING
A206: =A17 -> NEAR POST OFFICE, NILESHWAR
B207: DEPRECIATION SCHEDULE OF FIXED ASSET AS ON 31-03-2025
B209: =B20 -> PARTICULARS | C209: =C20 -> % | D209: =D20 -> Rs. Ps. | E209: =E20 -> Rs. Ps. | F209: =F20 -> Rs. Ps.
B211: =B22 -> 0 | D211: =F23 -> 0 | E211: =D211 -> 0
B212: =B23 -> Less: Depreciation Written off | C212: =C23 -> 10 | E212: =E211*10/100 -> 0 | F212: =E211-E212 -> 0
B213: =B24 -> 0 | D213: =F25 -> 0 | E213: =D213 -> 0
B214: =B25 -> Less: Depreciation Written off | C214: =C25 -> 10 | E214: =E213*10/100 -> 0 | F214: =E213-E214 -> 0
B215: =B26 -> INVERTOR 3KVA | D215: =F27 -> 70000 | E215: =D215 -> 70000
B216: =B27 -> Less: Depreciation Written off | C216: =C27 -> 10 | E216: =E215*10/100 -> 7000 | F216: =E215-E216 -> 63000
B217: =B28 -> GODREREJ A/C | D217: =F29 -> 32666.667 | E217: =D217 -> 32666.667
B218: =B29 -> Less: Depreciation Written off | C218: =C29 -> 10 | E218: =E217*10/100 -> 3266.6667 | F218: =E217-E218 -> 29400
B219: =B30 -> LLOYD A/C | D219: =F31 -> 32666.667 | E219: =D219 -> 32666.667
B220: =B31 -> Less: Depreciation Written off | C220: =C31 -> 10 | E220: =E219*10/100 -> 3266.6667 | F220: =E219-E220 -> 29400
B221: =B32 -> HALER A/C | D221: =F33 -> 37333.333 | E221: =D221 -> 37333.333
B222: =B33 -> Less: Depreciation Written off | C222: =C33 -> 10 | E222: =E221*10/100 -> 3733.3333 | F222: =E221-E222 -> 33600
B223: =B34 -> COMPUTER CHAIR , TABLE Etc. | D223: =F35 -> 79333.333 | E223: =D223 -> 79333.333
B224: =B35 -> Less: Depreciation Written off | C224: =C35 -> 10 | E224: =E223*10/100 -> 7933.3333 | F224: =E223-E224 -> 71400
B225: =B36 -> 0 | D225: =F37 -> 0 | E225: =D225 -> 0
B226: =B37 -> Less: Depreciation Written off | C226: =C37 -> 10 | E226: =E225*10/100 -> 0 | F226: =E225-E226 -> 0
B227: =B38 -> 0 | D227: =F39 -> 0 | E227: =D227 -> 0
B228: =B39 -> Less: Depreciation Written off | C228: =C39 -> 10 | E228: =E227*10/100 -> 0 | F228: =E227-E228 -> 0
B229: =B40 -> 0 | D229: =F41 -> 0 | E229: =D229 -> 0
B230: =B41 -> Less: Depreciation Written off | C230: =C41 -> 10 | E230: =E229*10/100 -> 0 | F230: =E229-E230 -> 0
B231: =B42 -> 0 | D231: =F43 -> 0 | E231: =D231 -> 0
B232: =B43 -> Less: Depreciation Written off | C232: =C43 -> 10 | E232: =E231*10/100 -> 0 | F232: =E231-E232 -> 0
B233: =B44 -> 0 | D233: =F45 -> 0 | E233: =D233 -> 0
B234: =B45 -> Less: Depreciation Written off | C234: =C45 -> 10 | E234: =E233*10/100 -> 0 | F234: =E233-E234 -> 0
B235: =B46 -> 0 | D235: =F47 -> 0 | E235: =D235 -> 0
B236: =B47 -> Less: Depreciation Written off | C236: =C47 -> 10 | E236: =E235*10/100 -> 0 | F236: =E235-E236 -> 0
B237: =B48 -> 0 | D237: =F49 -> 0 | E237: =D237 -> 0
B238: =B49 -> Less: Depreciation Written off | C238: =C49 -> 10 | E238: =E237*10/100 -> 0 | F238: =E237-E238 -> 0
B239: =B50 -> 0 | D239: =F51 -> 0 | E239: =D239 -> 0
B240: =B51 -> Less: Depreciation Written off | C240: =C51 -> 10 | E240: =E239*10/100 -> 0 | F240: =E239-E240 -> 0
B241: =B52 -> 0 | D241: =F53 -> 0 | E241: =D241 -> 0
B242: =B53 -> Less: Depreciation Written off | C242: =C53 -> 10 | E242: =E241*10/100 -> 0 | F242: =E241-E242 -> 0
B243: =B54 -> 0 | D243: =F55 -> 0 | E243: =D243 -> 0
B244: =B55 -> Less: Depreciation Written off | C244: =C55 -> 10 | E244: =E243*10/100 -> 0 | F244: =E243-E244 -> 0
B245: =B56 -> 0 | D245: =F57 -> 0 | E245: =D245 -> 0
B246: =B57 -> Less: Depreciation Written off | E246: =E245*10/100 -> 0 | F246: =E245-E246 -> 0
B247: =B58 -> 0 | C247: =C57 -> 10 | D247: =F59 -> 0 | E247: =D247 -> 0
B248: =B59 -> Less: Depreciation Written off | E248: =E247*10/100 -> 0 | F248: =E247-E248 -> 0
C310: =C67 -> TOTAL | D310: =SUM(D211:D309) -> 252000 | E310: =E212+E214+E216+E218+E220+E222+E224+E226+E228+E230+E232+E234+E236+E238+E240+E242+E244+E246+E248 -> 25200 | F310: =SUM(F211:F251) -> 226800
B405: =B205 -> Mr.SHAFEEK N N | C405: =C205 -> M/S.SHAS DESIGN AND PRINTING
C406: =A206 -> NEAR POST OFFICE, NILESHWAR
C407: DEPRECIATION SCHEDULE OF FIXED ASSET AS ON 31-03-2026
B409: =B209 -> PARTICULARS | C409: =C209 -> % | D409: =D209 -> Rs. Ps. | E409: =D409 -> Rs. Ps. | F409: =E409 -> Rs. Ps.
B411: =B211 -> 0 | D411: =F212 -> 0 | E411: =D411 -> 0
B412: Less: Depreciation Written off | C412: 10 | E412: =E411*10/100 -> 0 | F412: =E411-E412 -> 0
B413: =B213 -> 0 | D413: =F214 -> 0 | E413: =D413 -> 0
B414: Less: Depreciation Written off | C414: 10 | E414: =E413*10/100 -> 0 | F414: =E413-E414 -> 0
B415: =B215 -> INVERTOR 3KVA | D415: =F216 -> 63000 | E415: =D415 -> 63000
B416: Less: Depreciation Written off | E416: =E415*10/100 -> 6300 | F416: =E415-E416 -> 56700
B417: =B217 -> GODREREJ A/C | C417: 10 | D417: =F218 -> 29400 | E417: =D417 -> 29400
B418: Less: Depreciation Written off | E418: =E417*10/100 -> 2940 | F418: =E417-E418 -> 26460
B419: =B219 -> LLOYD A/C | D419: =F220 -> 29400 | E419: =D419 -> 29400
B420: Less: Depreciation Written off | C420: 10 | E420: =E419*10/100 -> 2940 | F420: =E419-E420 -> 26460
...

Sheet MUDRA 
A8: LOAN APPLICATION FORM MSME LOAN UPTO 50 LAKH
B9: (To be submitted along with documents as per the checklist)
A11: A. For office Use:
A13: Enterprise Name | C13: Application Sl. No. | E13: Name of the Branch | G13: Category
A14: ='PROJECT REPORT '!H6 -> M/S.SHAS DESIGN AND PRINTING | E14: ='PROJECT REPORT '!H53 -> NILESHWAR | G14: Shishu/Kishor/Tarun
A16: B.Business Information:
A18: Name of Enterprise | C18: =A14 -> M/S.SHAS DESIGN AND PRINTING
B20: Constitution I √ | C20: Proprietary | D20: Partnership | E20: Pvt. Ltd. | F20: Ltd. Company | G20: Any Others (specify)
A21: Current
A22: Business
A23: Adress | C23: State | D23: KERALA | E23: PIN Code | G23: ='PROJECT REPORT '!H15 -> 671314
C24: Business Premises | E24: √ | F24: Rented | G24: Owned | H24: Leased
A26: Adress Of the | C26: ='PROJECT REPORT '!H8 -> W-III/1022 | D26: ='PROJECT REPORT '!H7 -> NEAR POST OFFICE, NILESHWAR
A27: Factory/Shop/ | C27: ='PROJECT REPORT '!H11 -> NILESHWAR
A28: Business | C28: ='PROJECT REPORT '!H14 -> KASARAGOD
A29: Taluk | C29: ='PROJECT REPORT '!H13 -> HOSDURG | F29: District | G29: ='PROJECT REPORT '!H14 -> KASARAGOD
A30: Telephone No. | F30: Mobile No. | G30: ='PROJECT REPORT '!H16 -> 9847599008
A31: Email ID
A32: Business | C32: Existing | E32: ='PROJECT REPORT '!H28 -> DIGITAL PRINTING
A33: Activity | C33: Proposed
A34: Date of Commencement(DD/MM/YYYY
A35: Whether the Unit is Registered | D35: √ | E35: Yes | G35: No
A36: If Registered (Please mention:Registration
A37: no. And the Act under which registered )
A38: Registered office Address | D38: SAME S ABOVE
A40: Social Category | C40: √ | D40: SC | E40: ST | F40: OBC | G40: Minority | H40: General
A41: If MinorityCommunity √ | C41: Budhist | D41: Muslims | E41: Christians | F41: Sikhs | G41: Jains | H41: Zoroastrians
A43: C.Background Information of Proprietor/ Partners/ Directors:
A45: S.No | B45: Name | C45: Date of Birth | D45: Sex | E45: Residential Address with Mobile No. | G45: Academic qualification | H45: Experience in the line of activity(Years)
A46: 1. | B46: ='PROJECT REPORT '!H17 -> Mr.SHAFEEK N N | C46: ='PROJECT REPORT '!H24 -> 10/05/1988 | D46: ='DATA INPUT '!C15 -> MALE | E46: ='PROJECT REPORT '!H19 -> BAITHUL SHAMNA HOUSE
E47: ='PROJECT REPORT '!H20 -> KANHANGAD | G47: ='PROJECT REPORT '!H30 -> SSLC | H47: ='PROJECT REPORT '!H31 -> 12
E48: ='PROJECT REPORT '!H21 -> NILESHWAR | H48: 6 YEARS
E49: ='PROJECT REPORT '!H16 -> 9847599008
A50: 2.
A53: S.No | B53: Id proof no. | C53: Id proof | D53: Address proof | E53: PAN Card/DIN No. | G53: Relationship with the officials/ Director of the bank if any
A54: 1. | B54: ='PROJECT REPORT '!H26 -> 3616 3601 1234 | C54: ='PROJECT REPORT '!B26 -> ADHAAR CARD NO. | D54: ='PROJECT REPORT '!B25 -> PAN No: | E54: ='PROJECT REPORT '!H25 -> 0 | G54: NA
A56: 2.
A61: D. Names of Associate Concerns and Nature of Association
A62: Names of Associate Concern | C62: Address of Associate Concern | D62: Presently Banking with | E62: Nature of Association Concern | F62: Extent of Interest as a Prop./Partner/ Director or Just Investor in Associate Concern
A63: NA | C63: NA | D63: NA | E63: NA | F63: NA
A67: E. Banking/Credit Facilities Existing: (In Rs.)
A69: Type of Facilities | C69: Presently Banking with | D69: Limit Availed | E69: Outstanding As on …… | F69: Security lodged | G69: Asset classification status
A72: Savings Account | D72: N. A. | F72: N. A.
A73: Current Account | D73: N. A. | F73: N. A.
A74: Cash Credit | D74: N. A.
A75: Term Loan | D75: N. A.
A76: LC/BG
A77: If banking with this bank, customer ID to be given here:
A78: It is certified that our unit has not availed any loan from any other Bank / Financial Institution in the past and I/we am/are not indebted to any other Bank / Financial Institution other than those mentioned in column no. E above.
A80: F. Credit Facilities Proposed:(In Rs.)
A82: Type of Facilities | C82: Amount | D82: Purpose for which Required | F82: Details of Primary Security Offered (with approx. value to be mentioned)
A83: Cash Credit | C83: ='PROJECT REPORT '!H363 -> 50000 | D83: ='PROJECT REPORT '!B363 -> Working Capital (Cash Credit) | F83: ='PROJECT REPORT '!J363 -> 139830
A84: Term Loan | C84: ='PROJECT REPORT '!H361 -> 585750 | D84: ='PROJECT REPORT '!B361 -> Fixed Investments (Term Loan) | F84: ='PROJECT REPORT '!J361 -> 781000
A85: LC/BG | C85: 0
A86: Total | C86: =SUM(C83:C85) -> 635750 | F86: =SUM(F83:F85) -> 920830
A89: G.In case of Working Capital: Basis of CashCredit Limit applied:(In Rs.)
A91: Actual Sales | C91: Projected
A92: FY- FY- | B92: Sales | C92: Working Cycle in Months | D92: Inventory | E92: Debtors | F92: Creditors | G92: Promoter’s Contribution | H92: Limits
C93: ='PROJECT REPORT '!P16 -> 3 | D93: ='T,P&L,BS'!F82 -> 130350 | E93: ='T,P&L,BS'!F125 -> 4022.1833 | F93: ='T,P&L,BS'!C128 -> 27224.583 | G93: ='PROJECT REPORT '!F363 -> 89830 | H93: ='PROJECT REPORT '!H363 -> 50000
A96: H. In case of Term loan requirements, the details of machinery/equipment may be given as under:
A98: Type of machine / Equipment | B98: Purpose for which required | C98: Name of Supplier | D98: Total Cost of Machine | E98: Contribution being made by the promoters(Rs.) | G98: Loan Required (Rs.)
C101: Total | D101: ='PROJECT REPORT '!J361 -> 781000 | E101: ='PROJECT REPORT '!F361 -> 195250 | G101: ='PROJECT REPORT '!H361 -> 585750
A103: Repayment period with Moratorium period requested for | E103: MORATORIUM | F103: 3 MONTHS + | G103: ='PROJECT REPORT '!P38 -> 60 | H103: MONTHS
A108: I. Past Performance / Future Estimates: (In Rs.)
A110: Past Performance / Future Estimates (Actual performance for two previous years, estimates for current year and projections for next year to be provided for working capital facilities. However for term loan facilities projections to be provided till the proposed year of repayment of loan)
B111: Past Year-II (Actual) | C111: Past Year-I (Actual) | E111: Present Year (Estimate) | G111: Next Year (Projection)
A112: Net Sales | E112: ='T,P&L,BS'!F78 -> 1088983.3 | G112: ='T,P&L,BS'!F149 -> 1766757.4
A113: Net Profit | E113: ='T,P&L,BS'!C98 -> 292139.97 | G113: ='T,P&L,BS'!C169 -> 388106.72
A114: Capital (Net Worth in case of(Companies) | F114: ='T,P&L,BS'!C118 -> 537219.97 | H114: ='T,P&L,BS'!C188 -> 865326.69
A116: J. Status Regarding Statutory Obligations:
A118: Statutory Obligations | D118: Whether Complied with (select Yes/No) If not applicable then select N. A. | F118: Remarks (Any details in connection withthe relevant obligation to be given )
A120: 1. Registration under Shops and Establishment Act | E120: YES
A121: 2. Registration under MSME (Provisional /Final)
A122: 3. Drug License | E122: NA
A123: 4. Latest Sales Tax Return Filed
A124: 5.Latest Income Tax Returns Filed
A125: 6.Any other Statutory dues remaining outstanding | E125: NA
A127: K. Declaration:
A129: I/We hereby certify that all information furnished by me/us is true, correct and complete. I/We have no borrowing arrangements
A130: for the unit except as indicated in the application form. There is/are no overdue / statutory dueowed by me/us.
A131: I/We shall furnish all other information that may be required by Bank in connection with my/our application. The information may
A132: also be exchanged by you with any agency you may deem fit. You, your representatives or Reserve Bank of India or Mudra Ltd.,
A133: or any other agency as authorised by you, may at any time, inspect/ verify my/our assets, books of accounts etc. in our factory/
A134: business premises as given above. You may take appropriate safeguards/action forrecovery of bank’s dues.
A137: Space for Photo | C137: Space for Photo | F137: Space for Photo
A138: (Signatures of Proprietor/partner/ director whose photo is affixed above)
A140: Date: | B140: =TODAY()+5 -> 45926
A142: Place: | B142: ='PROJECT REPORT '!H53 -> NILESHWAR
A147: CHECK LIST: (The check list is only indicative and not exhaustive and depending upon the
A148: local requirements at different places addition could be made as per necessity)
A149: 1) Proof of identity - Self certified copy of Voter’s ID card / Driving License / PAN Card /
A150: Aadhar Card/Passport.
A151: 2) Proof of Residence - Recent telephone bill, electricity bill, property tax receipt (not older than 2
A152: months), Voter’s ID card, Aadhar Card & Passport of Proprietor/Partners/Directors.
A153: 3) Proof of SC/ST/OBC/Minority.
A154: 4) Proof of Identity/Address of the Business Enterprise -Copies of relevant licenses/registration
A155: certificates/other documents pertaining to the ownership, identity and address of business unit.
A156: 5) Applicant should not be defaulter in any Bank/Financial institution.
A157: 6) Statement of accounts (for the last six months), from the existing banker, if any.
A158: 7) Last two years balance sheets of the units along with income tax/sales tax return etc.
...

Sheet Sheet1
A2: LA BELLE BOUTIQUE
A3: CITY CENTER, OPP ST. MARYS GHS SCHOOL PAYYANUR.
A4: Mob: 9895305797
A5: 32BEIPT 9737A1ZE QOUTATION
A6: To
B7: Mr. Rameshan | C7: No. : | D7: 42
B8: ROOTS BEAUTY SPA | C8: Date : | D8: 44539
B9: WOODYZ TOWER , KANHANGAD
A12: S.No. | B12: DESCRIPTION | C12: RATE | D12: QTY | E12: AMOUNT
A13: 1 | B13: RAAGA PB SPA 4HEAD NOURISHMENT CREAM BATH 750 ML | C13: 417.7126 | D13: 35 | E13: 14619.941
A14: 2 | B14: RAAGA PB SPA 4HEAD NOURISHMENT CREAM BATH 750 ML | C14: 417.7126 | D14: 35 | E14: 14619.941
A15: 3 | B15: RAAGA ECO PAK WITH PILY SKIN 200M | C15: 223.3054 | D15: 75 | E15: 16747.905
A16: 4 | B16: RAAGA STEMCELLS PLATINUM FACIAL KIT 61G | C16: 246.9522 | D16: 60 | E16: 14817.132
A17: 5 | B17: RAAGA PROF STEMCELLS FAIRNESS KIT 61G | C17: 218.0478 | D17: 75 | E17: 16353.585
A18: 6 | B18: RAGA PROF STEMCELLS ANTICANE FACIAL KIT 61G | C18: 225.9342 | D18: 60 | E18: 13556.052
A19: 7 | B19: RAAGA PEDI MENI ALOVERA 63GM | C19: 144.491 | D19: 75 | E19: 10836.825
A20: 8 | B20: RAAGA LS WAX ALOVERA 800ML | C20: 520.1676 | D20: 100 | E20: 52016.76
A21: 9 | B21: RAAGA PB CLR PROTECT SHAMPOO &CONDITIONER 1000ML | C21: 1024.5748 | D21: 25 | E21: 25614.37
A22: 10 | B22: SCHWARZKOPF GLATT STRAIGHTENER AND NEUTRALIZING BALM | C22: 1011.4432 | D22: 22.5 | E22: 22757.472
A23: 11 | B23: SCHWARZKOPF SCALP GENESIS PURIFYING SHAMPOO | C23: 499.1496 | D23: 28 | E23: 13976.189
A24: 12 | B24: SHAHNAZ GOLD SKIN RADIANCE KIT | C24: 530.6766 | D24: 15 | E24: 7960.149
... A45: 33 | B45: CALEO DIAMOND SPA FACIAL KIT 280 ML | C45: 629.982 | D45: 15 | E45: 9449.73
D46: =SUM(D13:D45) -> 1138.5 | E46: =SUM(E13:E45) -> 646412.83
B47: . | C47: GST @18% | E47: =E46*18/100 -> 116354.31
C48: Grand Total | E48: =SUM(E46:E47) -> 762767.14
A49: E&OE
A50: (Rupees Seven Lakh Sixty Two Thousand Sevenhundred and Sixty Seven Only)
C53: Authorised Signatory
